comando/__init__.py
comando/core.py
comando/linearization.py
comando/utility.py
comando/visualization.py
comando/interfaces/__init__.py
comando/interfaces/baron.py
comando/interfaces/dyos.py
comando/interfaces/gams.py
comando/interfaces/gurobi.py
comando/interfaces/maingo_ale.py
comando/interfaces/maingo_api.py
comando/interfaces/modelica.py
comando/interfaces/pyomo.py
comando/interfaces/pyomo_dae.py
comando/interfaces/quboify.py
comando/interfaces/scip.py
comando-1.2.0.dist-info/licenses/LICENSE
comando-1.2.0.dist-info/METADATA
comando-1.2.0.dist-info/WHEEL
comando-1.2.0.dist-info/top_level.txt
comando-1.2.0.dist-info/RECORD
