Metadata-Version: 2.4
Name: comando
Version: 1.2.0
Summary: A next-generation modeling framework for component-oriented modeling and optimization for nonlinear design and operation of integrated energy systems
Author-email: Marco Langiu <marco.langiu@rwth-aachen.de>
License: MIT License
Project-URL: Homepage, https://jugit.fz-juelich.de/iek-10/core-projects/comando/comando
Project-URL: Documentation, https://comando.readthedocs.io/en/latest/
Project-URL: Issues, https://jugit.fz-juelich.de/iek-10/public/optimization/comando/-/issues
Classifier: Development Status :: 5 - Production/Stable
Classifier: Intended Audience :: Science/Research
Classifier: License :: OSI Approved :: MIT License
Classifier: Topic :: Scientific/Engineering
Classifier: Natural Language :: English
Classifier: Operating System :: OS Independent
Classifier: Programming Language :: Python :: 3
Classifier: Programming Language :: Python :: 3.7
Classifier: Programming Language :: Python :: 3.8
Classifier: Programming Language :: Python :: 3.9
Classifier: Programming Language :: Python :: 3.10
Classifier: Programming Language :: Python :: 3.11
Classifier: Programming Language :: Python :: 3.12
Requires-Python: >=3.7
License-File: LICENSE
Requires-Dist: pandas
Requires-Dist: sympy>=1.6
Provides-Extra: symengine
Requires-Dist: symengine; extra == "symengine"
Provides-Extra: linearization
Requires-Dist: scipy; extra == "linearization"
Requires-Dist: scikit-learn; extra == "linearization"
Provides-Extra: visualization
Requires-Dist: matplotlib; extra == "visualization"
Provides-Extra: pyomo
Requires-Dist: pyomo>=6; extra == "pyomo"
Provides-Extra: gurobi
Requires-Dist: gurobipy; extra == "gurobi"
Provides-Extra: dev
Requires-Dist: pytest; extra == "dev"
Requires-Dist: pytest-cov; extra == "dev"
Requires-Dist: sphinx; extra == "dev"
Requires-Dist: pypandoc; extra == "dev"
Requires-Dist: sphinx_rtd_theme; extra == "dev"
Requires-Dist: sphinx-math-dollar; extra == "dev"
Provides-Extra: test
Requires-Dist: comando[dev]; extra == "test"
Requires-Dist: comando[pyomo]; extra == "test"
Requires-Dist: comando[linearization]; extra == "test"
Requires-Dist: comando[gurobipy]; extra == "test"
Provides-Extra: all
Requires-Dist: symengine; extra == "all"
Requires-Dist: scipy; extra == "all"
Requires-Dist: scikit-learn; extra == "all"
Requires-Dist: matplotlib; extra == "all"
Requires-Dist: pyomo>=6; extra == "all"
Requires-Dist: pytest; extra == "all"
Requires-Dist: pytest-cov; extra == "all"
Requires-Dist: sphinx; extra == "all"
Requires-Dist: pypandoc; extra == "all"
Requires-Dist: sphinx_rtd_theme; extra == "all"
Requires-Dist: sphinx-math-dollar; extra == "all"
Dynamic: license-file
